{
  "minecraft:recipes/decorations/crafting_table": {
    "criteria": {
      "unlock_right_away": "2025-03-22 05:06:38 +0000"
    },
    "done": true
  },
  "minecraft:adventure/adventuring_time": {
    "criteria": {
      "minecraft:dark_forest": "2025-03-22 05:06:39 +0000",
      "minecraft:river": "2025-03-22 05:16:08 +0000",
      "minecraft:jungle": "2025-03-22 05:18:12 +0000",
      "minecraft:old_growth_birch_forest": "2025-03-22 05:15:57 +0000"
    },
    "done": false
  },
  "create:root": {
    "criteria": {
      "0": "2025-03-22 05:14:37 +0000"
    },
    "done": true
  },
  "mowziesmobs:root": {
    "criteria": {
      "custom_test_name": "2025-03-22 05:14:37 +0000"
    },
    "done": true
  },
  "ironchest:recipes/decorations/chests/vanilla_dirt_chest": {
    "criteria": {
      "has_iron_ingot": "2025-03-22 05:14:37 +0000"
    },
    "done": true
  },
  "lootr:social": {
    "criteria": {
      "opened_chest": "2025-03-22 05:16:18 +0000"
    },
    "done": false
  },
  "dungeons_arise:wda_root": {
    "criteria": {
      "WDA": "2025-03-22 05:14:37 +0000"
    },
    "done": true
  },
  "securitycraft:recipes/redstone/reinforced_sticky_piston": {
    "criteria": {
      "has_slime_ball": "2025-03-22 05:19:29 +0000"
    },
    "done": true
  },
  "minecraft:adventure/root": {
    "criteria": {
      "killed_something": "2025-03-22 05:19:26 +0000"
    },
    "done": true
  },
  "minecraft:recipes/redstone/slime_block": {
    "criteria": {
      "has_slime_ball": "2025-03-22 05:19:29 +0000"
    },
    "done": true
  },
  "born_in_chaos_v1:bornin_chaos": {
    "criteria": {
      "bornin_chaos_0": "2025-03-22 05:14:37 +0000"
    },
    "done": true
  },
  "lootr:1chest": {
    "criteria": {
      "opened_chest": "2025-03-22 05:16:18 +0000"
    },
    "done": true
  },
  "create_connected:root": {
    "criteria": {
      "0": "2025-03-22 05:14:37 +0000"
    },
    "done": true
  },
  "lootr:root": {
    "criteria": {
      "always_true": "2025-03-22 05:14:37 +0000"
    },
    "done": true
  },
  "cataclysm:root": {
    "criteria": {
      "custom_test_name": "2025-03-22 05:14:37 +0000"
    },
    "done": true
  },
  "minecraft:recipes/tools/lead": {
    "criteria": {
      "has_slime_ball": "2025-03-22 05:19:29 +0000"
    },
    "done": true
  },
  "minecraft:recipes/redstone/sticky_piston": {
    "criteria": {
      "has_slime_ball": "2025-03-22 05:19:29 +0000"
    },
    "done": true
  },
  "ironfurnaces:coal": {
    "criteria": {
      "rainbowcoal": "2025-03-22 05:14:37 +0000"
    },
    "done": true
  },
  "DataVersion": 3465
}